gbquality/GM.py
gbquality/GM_test.py
gbquality/__init__.py
gbquality-0.32.dist-info/METADATA
gbquality-0.32.dist-info/WHEEL
gbquality-0.32.dist-info/top_level.txt
gbquality-0.32.dist-info/RECORD
