Metadata-Version: 2.1
Name: gbquality
Version: 0.32
Summary: Python translation of the original MATLAB code for the GB measure.
Home-page: https://github.com/AndLen/gbquality
Author: Andrew Lensen
Author-email: Andrew.Lensen@ecs.vuw.ac.nz
License: MIT
Download-URL: https://github.com/AndLen/gbquality/archive/v0.11.tar.gz
Keywords: NLDR,manifold learning,global quality
Platform: UNKNOWN
Classifier: Development Status :: 4 - Beta
Classifier: Intended Audience :: Developers
Classifier: Topic :: Scientific/Engineering :: Artificial Intelligence
Classifier: License :: OSI Approved :: MIT License
Classifier: Programming Language :: Python :: 3
Classifier: Programming Language :: Python :: 3.4
Classifier: Programming Language :: Python :: 3.5
Classifier: Programming Language :: Python :: 3.6
Classifier: Programming Language :: Python :: 3.7
Classifier: Operating System :: OS Independent
Requires-Python: >=3.4
Requires-Dist: numpy
Requires-Dist: scipy
Requires-Dist: scikit-learn
Requires-Dist: numba (>=0.47.0)
